<?xml version="1.0" encoding="utf-8" ?>
<dwsync>
<file name="10.png" server="neescreation.eu5.net/neescreation.eu5.net/" local="131694586900000000" remote="132639994800000000" Dst="0" />
<file name="2.png" server="neescreation.eu5.net/neescreation.eu5.net/" local="131694586900000000" remote="132639994800000000" Dst="0" />
<file name="3.png" server="neescreation.eu5.net/neescreation.eu5.net/" local="131694586900000000" remote="132639994800000000" Dst="0" />
<file name="4.png" server="neescreation.eu5.net/neescreation.eu5.net/" local="131694586900000000" remote="132639994800000000" Dst="0" />
<file name="5.png" server="neescreation.eu5.net/neescreation.eu5.net/" local="131694586900000000" remote="132639994800000000" Dst="0" />
<file name="6.png" server="neescreation.eu5.net/neescreation.eu5.net/" local="131694586900000000" remote="132639994800000000" Dst="0" />
<file name="7.png" server="neescreation.eu5.net/neescreation.eu5.net/" local="131694586900000000" remote="132639994800000000" Dst="0" />
<file name="9.png" server="neescreation.eu5.net/neescreation.eu5.net/" local="131694586900000000" remote="132639994800000000" Dst="0" />
<file name="8.png" server="neescreation.eu5.net/neescreation.eu5.net/" local="131694586900000000" remote="132639994800000000" Dst="0" />
<file name="A.png" server="neescreation.eu5.net/neescreation.eu5.net/" local="131694586900000000" remote="132639994800000000" Dst="0" />
<file name="J.png" server="neescreation.eu5.net/neescreation.eu5.net/" local="131694586920000000" remote="132639994800000000" Dst="0" />
<file name="K.png" server="neescreation.eu5.net/neescreation.eu5.net/" local="131694586960000000" remote="132639995400000000" Dst="0" />
<file name="Q.png" server="neescreation.eu5.net/neescreation.eu5.net/" local="131694587060000000" remote="132639995400000000" Dst="0" />
</dwsync>